LEGACY/archive_download.py
LEGACY/check_archive_files.py
LEGACY/compare_different_reprocess.py
LEGACY/convert_con_to_coverage.py
LEGACY/download_phangs_jwst.py
LEGACY/example_smooth_for_noise.py
LEGACY/gaia_query.py
LEGACY/get_wcs_adjust.py
LEGACY/jwst_pypherise.py
LEGACY/jwst_reprocess.py
LEGACY/log_jwst_reprocess.py
LEGACY/loop_kernel_creation.py
LEGACY/miri_destriping.py
LEGACY/nircam_destriping.py
LEGACY/postprocess_anchor_images.py
LEGACY/postprocess_control_flow.py
LEGACY/postprocess_convolve_anchored.py
LEGACY/postprocess_initial_convolve.py
LEGACY/prepare_release.py
LEGACY/psf_subtraction.py
LEGACY/run_jwst_reprocessing.py
LEGACY/run_miri_destriping.py
LEGACY/run_nircam_destriping.py
LEGACY/scratch_diffs.py
LEGACY/utils_jwst.py
LEGACY/utils_stats.py
LEGACY/PSF/convolve_all.py
LEGACY/PSF/detemine_safe_kernels.py
LEGACY/PSF/generate_JWST_PSF_and_kernels.py
LEGACY/PSF/make_kernels.py
LEGACY/PSF/psf_options_file.py
LEGACY/pca/vwpca.py
LEGACY/pca/vwpca_inc.py
LEGACY/pca/vwpca_normgappy.py
config/1558/astronode.toml
config/1558/config.toml
config/1558/run_reprocessing.py
config/1558/stpipe-log.cfg
config/2107/astronode.toml
config/2107/config.toml
config/2107/mac.toml
config/2107/run_reprocessing.py
config/2107/stpipe-log.cfg
config/2107/alignment/ic5332_agb_cat.fits
config/2107/alignment/ngc0628_agb_cat.fits
config/2107/alignment/ngc1087_agb_cat.fits
config/2107/alignment/ngc1300_agb_cat.fits
config/2107/alignment/ngc1365_agb_cat.fits
config/2107/alignment/ngc1385_agb_cat.fits
config/2107/alignment/ngc1433_agb_cat.fits
config/2107/alignment/ngc1512_agb_cat.fits
config/2107/alignment/ngc1566_agb_cat.fits
config/2107/alignment/ngc1672_agb_cat.fits
config/2107/alignment/ngc2835_agb_cat.fits
config/2107/alignment/ngc3351_agb_cat.fits
config/2107/alignment/ngc3627_agb_cat.fits
config/2107/alignment/ngc4254_agb_cat.fits
config/2107/alignment/ngc4303_agb_cat.fits
config/2107/alignment/ngc4321_agb_cat.fits
config/2107/alignment/ngc4535_agb_cat.fits
pjpipe-1.3.0.dist-info/licenses/LICENSE
pjpipe-1.3.0.dist-info/METADATA
pjpipe-1.3.0.dist-info/WHEEL
pjpipe-1.3.0.dist-info/top_level.txt
pjpipe-1.3.0.dist-info/RECORD
