Metadata-Version: 2.4
Name: pjpipe
Version: 1.3.0
Summary: JWST Pipeline Wrapper for Nearby Galaxies
Author-email: "Thomas G. Williams" <thomas.williams@physics.ox.ac.uk>
Maintainer-email: "Thomas G. Williams" <thomas.williams@physics.ox.ac.uk>
License:                     GNU GENERAL PUBLIC LICENSE
Project-URL: Homepage, http://phangs.org
Project-URL: Bug Reports, https://github.com/phangsTeam/pjpipe/issues
Project-URL: Source, https://github.com/phangsTeam/pjpipe
Classifier: Development Status :: 5 - Production/Stable
Classifier: License :: OSI Approved :: GNU General Public License v3 or later (GPLv3+)
Classifier: Programming Language :: Python :: 3.11
Classifier: Programming Language :: Python :: 3.12
Classifier: Programming Language :: Python :: 3.13
Requires-Python: >=3.11
License-File: LICENSE
Requires-Dist: astropy>=6.1.2
Requires-Dist: astropy-healpix>=1.1.2
Requires-Dist: astroquery>=0.4.7
Requires-Dist: cmocean>=4.0.3
Requires-Dist: crds>=12.0.3
Requires-Dist: gwcs>=0.24.0
Requires-Dist: image-registration>=0.2.9
Requires-Dist: jwst>=1.18.0
Requires-Dist: lmfit>=1.3.3
Requires-Dist: matplotlib>=3.9.2
Requires-Dist: numpy>=2.2.6
Requires-Dist: opencv-python-headless>=4.11.0.86
Requires-Dist: photutils>=1.13.0
Requires-Dist: pyerfa>=2.0.1.5
Requires-Dist: pypdf>=5.6.0
Requires-Dist: pytest>=8.3.2
Requires-Dist: reproject>=0.14.1
Requires-Dist: requests>=2.32.3
Requires-Dist: scikit-image>=0.24.0
Requires-Dist: scipy>=1.14.1
Requires-Dist: shapely>=2.0.6
Requires-Dist: spherical-geometry>=1.3.3
Requires-Dist: setuptools>=72.2.0
Requires-Dist: stdatamodels>=3.0.2
Requires-Dist: stsci.imagestats>=1.8.3
Requires-Dist: stsci.stimage>=0.3.0
Requires-Dist: stpsf>=2.0.0
Requires-Dist: stwcs>=1.7.4
Requires-Dist: synphot>=1.5.0
Requires-Dist: threadpoolctl>=3.5.0
Requires-Dist: tomli>=2.0.1
Requires-Dist: tqdm>=4.66.5
Requires-Dist: tweakwcs>=0.8.10
Provides-Extra: docs
Requires-Dist: sphinx-automodapi>=0.17.0; extra == "docs"
Requires-Dist: sphinx-rtd-theme>=2.0.0; extra == "docs"
Dynamic: license-file
